{
	"title": "SitePipe | Books N' Bytes, Inc.",
	"description": "Simple Website Theme Managment API",
	"author": "Books N' Bytes, Inc.",
	"authorUrl": "https://www.booksnbytes.net",
	"logo": "favicon.png",
	"contentDir": "content",
	"themesDir": "themes",
	"themeId": "default",
	"nav": [
		{ "name": "main", "links": [
			{ "title": "About", "url": "/about" },
			{ "title": "Contact", "url": "/contact" }
		]},
		{ "name": "footer", "links": [
			{ "title": "Facebook", "url": "https://www.facebook.com/BooksNBytesInc" },
			{ "title": "Twitter", "url": "https://www.twitter.com/BooksNBytesInc" },
			{ "title": "Website", "url": "https://www.booksnbytes.net" }
		]}
	],
	"pages": [
		{ "name":"home", "title":"Home", "sections":[
			{ "template":"Header", "content":"" },
			{ "template":"Navigation", "content":"" },
			{ "template":"Body", "content":"" },
			{ "template":"Footer", "content":"" }
		]},
		{ "name":"about", "title":"About Us", "sections":[
			{ "template":"Header", "content":"" },
			{ "template":"Navigation", "content":"" },
			{ "template":"Body", "content":"" },
			{ "template":"Footer", "content":"" }
		]},
		{ "name":"contact", "title":"Contact Us", "sections":[
			{ "template":"Header", "content":"" },
			{ "template":"Navigation", "content":"" },
			{ "template":"Body", "content":"" },
			{ "template":"Footer", "content":"" }
		]}
	]
}
